<F_CATEGORY>
 <row id="18800" xml:space="preserve"><c1>PROFIT EXP ACCRUAL-MUDARABA DEPS-IB</c1><c2>PRO EX AC MUDAR</c2><c3>AC</c3><c18>YES</c18><c18 m="3">STG-OTHER-SERVICES</c18><c18 m="4">N</c18><c20>2</c20><c21> 45_RMUSER___OFS_RM.OFS.LD</c21><c22>1305311253</c22><c23>45_RMUSER_OFS_RM.OFS.LD</c23><c24>AE0010001</c24><c25>1</c25></row> <row id="52500" xml:space="preserve"><c1>LG COMM.RET.BONDS-ISLAMIC BNKG</c1><c2>COMMN.RET.BONS</c2><c3>PL</c3><c18>YES</c18><c18 m="4">Y</c18><c20>1</c20><c21>4_JETENDRA.AUT</c21><c22>0712051450</c22> <c23>4_JETENDRA.AUT</c23><c24>AE0010001</c24><c25>1</c25></row> <row id="15304" xml:space="preserve"><c1>CERTIFIED CHEQUES</c1><c2>CERTIFIED CHEQU</c2><c3>AC</c3><c8>NON.CONTINGENT</c8><c18>YES</c18><c18 m="3">STG-OTHER-SERVICES</c18><c18 m="4">N</c18><c20>2</c20> <c21>45_RMUSER___OFS_RM.OFS.LD</c21><c22>1305311253</c22><c23>45_RMUSER_OFS_RM.OFS.LD</c23><c24>AE0010001</c24><c25>1</c25></row> <row id="62104" xml:space="preserve"><c1>Forms &amp; Computer Accessories</c1><c2>Forms&amp;Comp Acc</c2><c3>PL</c3><c18 m="4">Y</c18><c20>1</c20><c21>4_JETENDRA.AUT</c21><c22>0712051450</c22><c23>4_J ETENDRA.AUT</c23><c24>AE0010001</c24><c25>1</c25></row> <row id="11795" xml:space="preserve"><c1>GST INPUT TAX RECEIVABLE</c1><c2>GST INPT TX REC</c2><c3>AC</c3><c8>NON.CONTINGENT</c8><c10>TR</c10><c18>YES</c18><c18 m="3">STG-OTHER-SERVICES</c18><c18 m="4">N</c18><c20>2</c20><c21>95104_SNGFGM5375</c21><c22>1509161821</c22><c23>64926_SNGF1135</c23><c24>AE0010001</c24><c25>501</c25></row> <row id="18000" xml:space="preserve"><c1>SHARE CAPITAL</c1><c2>share capital</c2><c3>AC</c3><c8>NON.CONTINGENT</c8><c18>YES</c18><c18 m="3">STG-OTHER-SERVICES</c18><c18 m="4">N</c18><c20>2</c20><c21>4 5_RMUSER___OFS_RM.OFS.LD</c21><c22>1305311253</c22><c23>45_RMUSER_OFS_RM.OFS.LD</c23><c24>AE0010001</c24><c25>1</c25></row> <row id="11450" xml:space="preserve"><c1>PREPAID AIR FARE</c1><c2>AIR FARE</c2><c3>AC</c3><c8>NON.CONTINGENT</c8><c18>YES</c18><c18 m="3">STG-OTHER-SERVICES</c18><c18 m="4">N</c18><c20>2</c20><c21>45_ RMUSER___OFS_RM.OFS.LD</c21><c22>1305311253</c22><c23>45_RMUSER_OFS_RM.OFS.LD</c23><c24>AE0010001</c24><c25>1</c25></row> <row id="62359" xml:space="preserve"><c1>VISA INTEGRATED BILLING</c1><c2>VISA INTG .BILL</c2><c3>PL</c3><c18>YES</c18><c18 m="4">Y</c18><c20>1</c20><c21>4_JETENDRA.AUT</c21><c22>0712051450</c22><c23>4 _JETENDRA.AUT</c23><c24>AE0010001</c24><c25>1</c25></row> <row id="10300" xml:space="preserve"><c1>CASH SHORTAGES</c1><c2>CASH SHORTAGES</c2><c3>AC</c3><c18>NO</c18><c18 m="4">N</c18><c20>1</c20><c21>4_JETENDRA.AUT</c21><c22>0712051450</c22><c23>4_JETENDRA.A UT</c23><c24>AE0010001</c24><c25>1</c25></row> <row id="15455" xml:space="preserve"><c1>UNAERNED FEES - SYNDICATIONS</c1><c2>UNEARNED FEES S</c2><c3>AC</c3><c8>NON.CONTINGENT</c8><c18>YES</c18><c18 m="3">STG-OTHER-SERVICES</c18><c18 m="4">N</c18><c20>2</c20><c21>45_RMUSER___OFS_RM.OFS.LD</c21><c22>1305311253</c22><c23>45_RMUSER_OFS_RM.OFS.LD</c23><c24>AE0010001</c24><c25>1</c25></row> <row id="52318" xml:space="preserve"><c1>LETTER OF CREDIT POSTAGE FEES</c1><c2>LC POSTAGE FEES</c2><c3>PL</c3><c18>YES</c18><c18 m="4">Y</c18><c20>1</c20><c21>4_JETENDRA.AUT</c21><c22>0712051449</c22> <c23>4_JETENDRA.AUT</c23><c24>AE0010001</c24><c25>1</c25></row> <row id="19100" xml:space="preserve"><c1>SWAOPTION DR</c1><c2>SWAPTION DR</c2><c3>AC</c3><c18>YES</c18><c18 m="3">STG-OTHER-SERVICES</c18><c18 m="4">N</c18><c20>2</c20><c21>45_RMUSER___OFS_RM.OFS.LD</c21><c22>1305311253</c22><c23>45_RMUSER_OFS_RM.OFS.LD</c23><c24>AE0010001</c24><c25>1</c25></row> <row id="10099" xml:space="preserve"><c1>*** Cash Accounts</c1><c2>Cash Accounts</c2><c3>AC</c3><c18 m="4">N</c18><c20>1</c20><c21>4_JETENDRA.AUT</c21><c22>0712051450</c22><c23>4_JETENDRA.AUT</c23><c24>AE0010001</c24><c25>1</c25></row> <row id="15140" xml:space="preserve"><c1>PROVISON FOR DONTON N SPONSORSHIP</c1><c2>PROV DON N SPON</c2><c3>AC</c3><c8>NON.CONTINGENT</c8><c18>YES</c18><c18 m="3">STG-OTHER-SERVICES</c18><c18 m="4">N</c18><c20>2</c20><c21>45_RMUSER___OFS_RM.OFS.LD</c21><c22>1305311253</c22><c23>45_RMUSER_OFS_RM.OFS.LD</c23><c24>AE0010001</c24><c25>1</c25></row> <row id="54103" xml:space="preserve"><c1>LD Reimb Prem/Disc Adj Prev Yr</c1><c2>LD Reimb P/D PY</c2><c3>PL</c3><c18 m="4">Y</c18><c20>1</c20><c21>4_JETENDRA.AUT</c21><c22>0712051449</c22><c23>4_JETEND RA.AUT</c23><c24>AE0010001</c24><c25>1</c25></row> <row id="20060" xml:space="preserve"><c1>Forex Negotiated</c1><c2>Forex Neg</c2><c3>FX</c3><c18 m="4">Y</c18><c20>1</c20><c21>4_JETENDRA.AUT</c21><c22>0712051450</c22><c23>4_JETENDRA.AUT</c23><c24>AE0 010001</c24><c25>1</c25></row> <row id="62655" xml:space="preserve"><c1>DEPRECIATION FURNITURE</c1><c2>DEPRE FURNITURE</c2><c3>PL</c3><c18>YES</c18><c18 m="4">Y</c18><c20>1</c20><c21>4_JETENDRA.AUT</c21><c22>0712051450</c22><c23>4_ JETENDRA.AUT</c23><c24>AE0010001</c24><c25>1</c25></row> <row id="21007" xml:space="preserve"><c1>Deposits Bond Linked</c1><c2>Depo Bond Link</c2><c3>LD</c3><c18 m="4">Y</c18><c20>1</c20><c21>4_JETENDRA.AUT</c21><c22>0712051450</c22><c23>4_JETENDRA.AUT</c23><c24>AE0010001</c24><c25>1</c25></row> <row id="62309" xml:space="preserve"><c1>Printing &amp; Editing</c1><c2>Printing&amp;Editi</c2><c3>PL</c3><c18 m="4">Y</c18><c20>1</c20><c21>4_JETENDRA.AUT</c21><c22>0712051450</c22><c23>4_JETENDRA.AU T</c23><c24>AE0010001</c24><c25>1</c25></row> </F_CATEGORY>
